aurora-x-hardware/vector_alu.v
module vector_alu (
    input  wire [2047:0] A,
    input  wire [2047:0] B,
    input  wire [2047:0] C, // Accumulator (vd)
    input  wire [2:0]    VALU_Op,
    output reg  [2047:0] Result
);

    localparam VALU_ADD  = 3'b000;
    localparam VALU_MUL  = 3'b001;
    localparam VALU_FMA  = 3'b010;
    localparam VALU_PERM = 3'b011;

    integer i;
    reg signed [31:0] a_elem, b_elem, c_elem, res_elem;
    
    // Array representation for dynamic indexing in VPERM
    reg [31:0] A_arr [0:63];

    always @(*) begin
        // Populate array
        for (i = 0; i < 64; i = i + 1) begin
            A_arr[i] = A[i*32 +: 32];
        end

        for (i = 0; i < 64; i = i + 1) begin
            a_elem = A[i*32 +: 32];
            b_elem = B[i*32 +: 32];
            c_elem = C[i*32 +: 32];
            
            case (VALU_Op)
                VALU_ADD:  res_elem = a_elem + b_elem;
                VALU_MUL:  res_elem = a_elem * b_elem;
                VALU_FMA:  res_elem = c_elem + (a_elem * b_elem);
                VALU_PERM: begin
                    if (b_elem >= 0 && b_elem < 64) begin
                        res_elem = A_arr[b_elem];
                    end else begin
                        res_elem = 32'd0;
                    end
                end
                default: res_elem = 32'd0;
            endcase
            
            Result[i*32 +: 32] = res_elem;
        end
    end

endmodule

aurora-x-hardware/vector_register_file.v
module vector_register_file (
    input  wire          clk,
    input  wire          we,
    input  wire [4:0]    rs1,
    input  wire [4:0]    rs2,
    input  wire [4:0]    rd,
    input  wire [2047:0] write_data,
    output wire [2047:0] read_data1,
    output wire [2047:0] read_data2,
    output wire [2047:0] read_data_vd
);

    // 32 Vector Registers, 2048-bits (256 bytes) each
    reg [2047:0] vr [0:31];

    integer i;
    initial begin
        for (i = 0; i < 32; i = i + 1) begin
            vr[i] = 2048'd0;
        end
    end

    // Write Port (Synchronous)
    always @(posedge clk) begin
        if (we) begin
            vr[rd] <= write_data;
        end
    end

    // Read Ports (Combinational)
    assign read_data1 = vr[rs1];
    assign read_data2 = vr[rs2];
    assign read_data_vd = vr[rd]; // For VFMA accumulator

endmodule

aurora-x-hardware/alu.v
module alu (
    input  wire [63:0] A,
    input  wire [63:0] B,
    input  wire [2:0]  ALU_Op,
    output reg  [63:0] Result,
    output wire        Zero
);

    // ALU Operations
    localparam ALU_ADD = 3'b000;
    localparam ALU_SUB = 3'b001;
    localparam ALU_AND = 3'b010;
    localparam ALU_OR  = 3'b011;
    localparam ALU_XOR = 3'b100;
    localparam ALU_SHL = 3'b101;
    localparam ALU_SHR = 3'b110;

    always @(*) begin
        case (ALU_Op)
            ALU_ADD: Result = A + B;
            ALU_SUB: Result = A - B;
            ALU_AND: Result = A & B;
            ALU_OR:  Result = A | B;
            ALU_XOR: Result = A ^ B;
            ALU_SHL: Result = A << B[5:0];
            ALU_SHR: Result = A >> B[5:0];
            default: Result = 64'd0;
        endcase
    end

    assign Zero = (Result == 64'd0);

endmodule

aurora-x-hardware/register_file.v
module register_file (
    input  wire        clk,
    input  wire        we,
    input  wire [4:0]  rs1,
    input  wire [4:0]  rs2,
    input  wire [4:0]  rd,
    input  wire [63:0] write_data,
    output wire [63:0] read_data1,
    output wire [63:0] read_data2
);

    // 32 General Purpose Registers, 64-bits each
    reg [63:0] registers [0:31];

    // Initialize all registers to 0 (important for simulation)
    integer i;
    initial begin
        for (i = 0; i < 32; i = i + 1) begin
            registers[i] = 64'd0;
        end
    end

    // Write Port (Synchronous)
    always @(posedge clk) begin
        if (we && rd != 5'd0) begin
            registers[rd] <= write_data;
        end
    end

    // Read Ports (Asynchronous/Combinational)
    // R0 is hardwired to 0
    assign read_data1 = (rs1 == 5'd0) ? 64'd0 : registers[rs1];
    assign read_data2 = (rs2 == 5'd0) ? 64'd0 : registers[rs2];

endmodule

aurora-x-hardware/decoder.v
module decoder (
    input  wire [31:0] inst,
    
    // Extracted Fields
    output wire [7:0]  opcode,
    output wire [4:0]  rd,
    output wire [4:0]  rs1,
    output wire [4:0]  rs2,
    output wire [13:0] imm14,
    output wire [18:0] imm19,
    output wire [11:0] csr_addr,
    output wire [8:0]  funct9,

    // Sign Extended Immediates
    output wire [63:0] imm14_sext,
    output wire [63:0] imm19_sext,

    // Control Signals
    output reg         RegWrite,
    output reg         ALUSrc_B,     // 0 = rs2, 1 = imm14_sext
    output reg  [2:0]  ALU_Op,
    output reg         MemRead,
    output reg         MemWrite,
    output reg         Branch,
    output reg         Jump,
    output reg         CSR_Write,
    output reg         CSR_Read,
    output reg  [1:0]  MemtoReg,      // 00=ALU, 01=Mem, 10=PC+4, 11=CSR

    // Vector Control Signals
    output reg         VectorOp,
    output reg         VectorRegWrite,
    output reg         VectorMemRead,
    output reg         VectorMemWrite,
    output reg  [2:0]  VALU_Op
);

    assign opcode   = inst[31:24];
    assign rd       = inst[23:19];
    // For STORE.X (0x22), BRANCH.X (0x40), CSR.WRITE (0x43), and VSTORE (0x61), rs1 is in 23:19
    assign rs1      = (opcode == 8'h22 || opcode == 8'h40 || opcode == 8'h43 || opcode == 8'h61) ? inst[23:19] : inst[18:14];
    // For STORE.X (0x22), BRANCH.X (0x40), and VSTORE (0x61), rs2 is in 18:14
    assign rs2      = (opcode == 8'h22 || opcode == 8'h40 || opcode == 8'h61) ? inst[18:14] : inst[13:9];
    assign imm14    = inst[13:0];
    assign imm19    = inst[18:0];
    assign csr_addr = inst[18:7]; // 12-bit CSR address
    assign funct9   = inst[8:0];

    // Sign extension
    assign imm14_sext = {{50{imm14[13]}}, imm14};
    assign imm19_sext = {{45{imm19[18]}}, imm19};

    always @(*) begin
        // Default values
        RegWrite  = 0;
        ALUSrc_B  = 0;
        ALU_Op    = 3'b000;
        MemRead   = 0;
        MemWrite  = 0;
        Branch    = 0;
        Jump      = 0;
        CSR_Write = 0;
        CSR_Read  = 0;
        MemtoReg  = 2'b00;
        VectorOp  = 0;
        VectorRegWrite = 0;
        VectorMemRead = 0;
        VectorMemWrite = 0;
        VALU_Op   = 3'b000;

        case (opcode)
            8'h01: begin // ADD.X / SUB.X
                RegWrite = 1;
                ALUSrc_B = 0;
                ALU_Op   = (funct9 == 9'd1) ? 3'b001 : 3'b000;
            end
            8'h02: begin // AND
                RegWrite = 1; ALUSrc_B = 0; ALU_Op = 3'b010;
            end
            8'h03: begin // OR
                RegWrite = 1; ALUSrc_B = 0; ALU_Op = 3'b011;
            end
            8'h04: begin // XOR
                RegWrite = 1; ALUSrc_B = 0; ALU_Op = 3'b100;
            end
            8'h05: begin // SHL
                RegWrite = 1; ALUSrc_B = 0; ALU_Op = 3'b101;
            end
            8'h06: begin // SHR
                RegWrite = 1; ALUSrc_B = 0; ALU_Op = 3'b110;
            end
            8'h09: begin // ADDI
                RegWrite = 1; ALUSrc_B = 1; ALU_Op = 3'b000; // ADD
            end
            8'h21: begin // LOAD.X
                RegWrite = 1; ALUSrc_B = 1; ALU_Op = 3'b000; // rs1 + imm14
                MemRead  = 1; MemtoReg = 2'b01;
            end
            8'h22: begin // STORE.X 
                MemWrite = 1; ALUSrc_B = 1; ALU_Op = 3'b000;
            end
            8'h40: begin // BRANCH.X
                Branch = 1; ALUSrc_B = 0; ALU_Op = 3'b001; // SUB to test equality
            end
            8'h41: begin // JUMP.X
                Jump = 1; RegWrite = 1; MemtoReg = 2'b10; // PC+4
            end
            8'h42: begin // CSR.READ
                CSR_Read = 1; RegWrite = 1; MemtoReg = 2'b11;
            end
            8'h43: begin // CSR.WRITE
                CSR_Write = 1;
            end
            8'h60: begin // VLOAD
                ALUSrc_B = 1; ALU_Op = 3'b000; // rs1 + imm14
                VectorMemRead = 1; VectorRegWrite = 1;
            end
            8'h61: begin // VSTORE
                ALUSrc_B = 1; ALU_Op = 3'b000;
                VectorMemWrite = 1;
            end
            8'h62: begin // VADD
                VectorOp = 1; VALU_Op = 3'b000; VectorRegWrite = 1;
            end
            8'h63: begin // VMUL
                VectorOp = 1; VALU_Op = 3'b001; VectorRegWrite = 1;
            end
            8'h64: begin // VFMA
                VectorOp = 1; VALU_Op = 3'b010; VectorRegWrite = 1;
            end
            8'h65: begin // VPERM
                VectorOp = 1; VALU_Op = 3'b011; VectorRegWrite = 1;
            end
            default: ; // NOP or Unknown
        endcase
    end

endmodule

aurora-x-hardware/aurora_x_core_single.v
module aurora_x_core (
    input  wire        clk,
    input  wire        rst_n,
    
    // Instruction Memory Interface
    output reg  [63:0] pc,
    input  wire [31:0] inst,
    
    // Data Memory Interface
    output wire [63:0] data_addr,
    output wire [63:0] data_write_val,
    input  wire [63:0] data_read_val,
    output wire        data_we,
    output wire        data_re,

    // Test Interface (CSR 0x700)
    output reg  [63:0] test_status
);

    // Wires
    wire [7:0]  opcode;
    wire [4:0]  rd, rs1, rs2;
    wire [13:0] imm14;
    wire [18:0] imm19;
    wire [11:0] csr_addr;
    wire [8:0]  funct9;

    wire [63:0] imm14_sext, imm19_sext;
    wire RegWrite, ALUSrc_B, MemRead, MemWrite, Branch, Jump, CSR_Write, CSR_Read;
    wire [2:0] ALU_Op;
    wire [1:0] MemtoReg;

    wire VectorOp, VectorRegWrite, VectorMemRead, VectorMemWrite;
    wire [2:0] VALU_Op;

    wire [63:0] read_data1, read_data2;
    wire [63:0] alu_result;
    wire alu_zero;

    // Decoder
    decoder u_decoder (
        .inst(inst),
        .opcode(opcode),
        .rd(rd),
        .rs1(rs1),
        .rs2(rs2),
        .imm14(imm14),
        .imm19(imm19),
        .csr_addr(csr_addr),
        .funct9(funct9),
        .imm14_sext(imm14_sext),
        .imm19_sext(imm19_sext),
        .RegWrite(RegWrite),
        .ALUSrc_B(ALUSrc_B),
        .ALU_Op(ALU_Op),
        .MemRead(MemRead),
        .MemWrite(MemWrite),
        .Branch(Branch),
        .Jump(Jump),
        .CSR_Write(CSR_Write),
        .CSR_Read(CSR_Read),
        .MemtoReg(MemtoReg),
        .VectorOp(VectorOp),
        .VectorRegWrite(VectorRegWrite),
        .VectorMemRead(VectorMemRead),
        .VectorMemWrite(VectorMemWrite),
        .VALU_Op(VALU_Op)
    );

    // Register File
    reg  [63:0] reg_write_data;
    register_file u_regfile (
        .clk(clk),
        .we(RegWrite),
        .rs1(rs1),
        .rs2(rs2),
        .rd(rd),
        .write_data(reg_write_data),
        .read_data1(read_data1),
        .read_data2(read_data2)
    );

    // ALU
    wire [63:0] alu_in_b = (ALUSrc_B) ? imm14_sext : read_data2;
    alu u_alu (
        .A(read_data1),
        .B(alu_in_b),
        .ALU_Op(ALU_Op),
        .Result(alu_result),
        .Zero(alu_zero)
    );

    // Vector Register File and ALU
    wire [2047:0] vector_read_data1, vector_read_data2, vector_read_data_vd;
    wire [2047:0] vector_alu_result;
    wire [2047:0] vector_write_data = VectorMemRead ? {1984'd0, data_read_val} : vector_alu_result;

    vector_register_file u_vrf (
        .clk(clk),
        .we(VectorRegWrite),
        .rs1(rs1),
        .rs2(rs2),
        .rd(rd),
        .write_data(vector_write_data),
        .read_data1(vector_read_data1),
        .read_data2(vector_read_data2),
        .read_data_vd(vector_read_data_vd)
    );

    vector_alu u_valu (
        .A(vector_read_data1),
        .B(vector_read_data2),
        .C(vector_read_data_vd),
        .VALU_Op(VALU_Op),
        .Result(vector_alu_result)
    );

    wire is_exret = (opcode == 8'h45);
    wire alignment_fault = (data_we_raw || data_re_raw) && (data_addr[2:0] != 3'b000);

    // Memory Interface
    wire data_we_raw = MemWrite || VectorMemWrite;
    wire data_re_raw = MemRead || VectorMemRead;
    
    assign data_addr      = alu_result;
    assign data_write_val = VectorMemWrite ? vector_read_data2[63:0] : read_data2;
    // Prevent memory access if there is an alignment fault
    assign data_we        = data_we_raw && !alignment_fault;
    assign data_re        = data_re_raw && !alignment_fault;

    // CSR Registers
    reg [63:0] csr_trap_handler;
    reg [63:0] csr_epc;
    reg [63:0] csr_trap_cause;

    // Writeback
    always @(*) begin
        case (MemtoReg)
            2'b00: reg_write_data = alu_result;
            2'b01: reg_write_data = data_read_val;
            2'b10: reg_write_data = pc + 4;
            2'b11: begin // CSR Read
                if (csr_addr == 12'h020) reg_write_data = csr_trap_handler;
                else if (csr_addr == 12'h021) reg_write_data = csr_epc;
                else if (csr_addr == 12'h008) reg_write_data = csr_trap_cause;
                else reg_write_data = 64'd0;
            end
        endcase
    end

    // PC Logic
    wire [63:0] next_pc;
    wire take_branch = Branch & alu_zero;
    wire [63:0] branch_offset = { {48{imm14[13]}}, imm14, 2'b00 };
    wire [63:0] jump_offset   = { {43{imm19[18]}}, imm19, 2'b00 };

    wire [63:0] pc_plus_4   = pc + 4;
    wire [63:0] pc_branch   = pc + branch_offset;
    wire [63:0] pc_jump     = pc + jump_offset;

    assign next_pc = alignment_fault ? csr_trap_handler :
                     is_exret        ? csr_epc :
                     Jump            ? pc_jump : 
                     (take_branch    ? pc_branch : pc_plus_4);

    always @(posedge clk or negedge rst_n) begin
        if (!rst_n) begin
            pc <= 64'd0;
            test_status <= 64'd0;
            csr_trap_handler <= 64'd0;
            csr_epc <= 64'd0;
            csr_trap_cause <= 64'd0;
        end else begin
            pc <= next_pc;

            // Handle Exceptions and CSRs
            if (alignment_fault) begin
                csr_epc <= pc; // Save offending PC
                csr_trap_cause <= 64'd2; // Alignment Fault Cause
            end else if (CSR_Write) begin
                if (csr_addr == 12'h700) test_status <= read_data1;
                else if (csr_addr == 12'h020) csr_trap_handler <= read_data1;
                else if (csr_addr == 12'h021) csr_epc <= read_data1;
                else if (csr_addr == 12'h008) csr_trap_cause <= read_data1;
            end
        end
    end

endmodule

aurora-x-hardware/tb_aurora_x.v
`timescale 1ns / 1ps

module tb_aurora_x;

    reg clk;
    reg rst_n;
    
    // Memory
    reg [31:0] rom [0:1023]; // 4KB instruction memory
    reg [63:0] ram [0:1023]; // 8KB data memory

    // Core outputs
    wire [63:0] pc;
    wire [63:0] data_addr;
    wire [63:0] data_write_val;
    wire data_we;
    wire data_re;
    wire [63:0] test_status;

    // Core inputs
    wire [31:0] inst;
    reg  [63:0] data_read_val;

    // Instantiate Core
    aurora_x_core u_core (
        .clk(clk),
        .rst_n(rst_n),
        .pc(pc),
        .inst(inst),
        .data_addr(data_addr),
        .data_write_val(data_write_val),
        .data_read_val(data_read_val),
        .data_we(data_we),
        .data_re(data_re),
        .test_status(test_status)
    );

    // ROM Logic
    // PC is in bytes, rom is word-addressed (4 bytes per word)
    assign inst = rom[pc[11:2]];

    // RAM Logic
    always @(posedge clk) begin
        if (data_we) begin
            ram[data_addr[12:3]] <= data_write_val;
        end
    end
    always @(*) begin
        if (data_re) begin
            data_read_val = ram[data_addr[12:3]];
        end else begin
            data_read_val = 64'd0;
        end
    end

    // Clock Generation
    always #5 clk = ~clk;

    // Test Control
    initial begin
        $dumpfile("aurora_x.vcd");
        $dumpvars(0, tb_aurora_x);

        // Load Compliance Test Hex
        // Initialize memory with 0s first to avoid X propagation
        for (integer i=0; i<1024; i=i+1) begin
            rom[i] = 32'd0;
            ram[i] = 64'd0;
        end

        $readmemh("../AURORA-X-Tests/fib.hex", rom);

        clk = 0;
        rst_n = 0;
        
        #20 rst_n = 1; // Release reset

        // Wait for test_status
        wait(test_status != 0);

        // Check for test completion via CSR 0x700
        if (test_status == 64'd1) begin
            $display("========================================");
            $display(" [HARDWARE PASS]");
            $display("========================================");
        end else begin
            $display("========================================");
            $display(" [HARDWARE FAIL] test_status = %d", test_status);
            $display("========================================");
        end

        #20 $finish;
    end

    // SYS_PRINT Interception
    always @(posedge clk) begin
        if (u_core.CSR_Write && u_core.csr_addr == 12'h701) begin
            $display("========================================");
            $display("[HARDWARE] SYS_PRINT: %d", u_core.read_data1);
            $display("========================================");
            $display(" [HARDWARE C-COMPILER PASS]");
            $display("========================================");
            $finish;
        end
    end

    // Timeout watchdog
    initial begin
        #5000;
        $display("========================================");
        $display(" [HARDWARE TIMEOUT] PC = %x", pc);
        $display("========================================");
        $finish;
    end

endmodule

aurora-x-hardware/aurora_x.vcd
$date
	Fri Jun 19 23:58:29 2026
$end
$version
	Icarus Verilog
$end
$timescale
	1ps
$end
$scope module tb_aurora_x $end
$var wire 32 ! inst [31:0] $end
$var wire 64 " test_status [63:0] $end
$var wire 64 # pc [63:0] $end
$var wire 64 $ data_write_val [63:0] $end
$var wire 1 % data_we $end
$var wire 1 & data_re $end
$var wire 64 ' data_addr [63:0] $end
$var reg 1 ( clk $end
$var reg 64 ) data_read_val [63:0] $end
$var reg 1 * rst_n $end
$scope module u_core $end
$var wire 1 + alignment_fault $end
$var wire 1 ( clk $end
$var wire 64 , data_addr [63:0] $end
$var wire 1 & data_re $end
$var wire 1 - data_re_raw $end
$var wire 64 . data_read_val [63:0] $end
$var wire 1 % data_we $end
$var wire 1 / data_we_raw $end
$var wire 32 0 inst [31:0] $end
$var wire 1 * rst_n $end
$var wire 1 1 take_branch $end
$var wire 2048 2 vector_write_data [2047:0] $end
$var wire 2048 3 vector_read_data_vd [2047:0] $end
$var wire 2048 4 vector_read_data2 [2047:0] $end
$var wire 2048 5 vector_read_data1 [2047:0] $end
$var wire 2048 6 vector_alu_result [2047:0] $end
$var wire 5 7 rs2 [4:0] $end
$var wire 5 8 rs1 [4:0] $end
$var wire 64 9 read_data2 [63:0] $end
$var wire 64 : read_data1 [63:0] $end
$var wire 5 ; rd [4:0] $end
$var wire 64 < pc_plus_4 [63:0] $end
$var wire 64 = pc_jump [63:0] $end
$var wire 64 > pc_branch [63:0] $end
$var wire 8 ? opcode [7:0] $end
$var wire 64 @ next_pc [63:0] $end
$var wire 64 A jump_offset [63:0] $end
$var wire 1 B is_exret $end
$var wire 64 C imm19_sext [63:0] $end
$var wire 19 D imm19 [18:0] $end
$var wire 64 E imm14_sext [63:0] $end
$var wire 14 F imm14 [13:0] $end
$var wire 9 G funct9 [8:0] $end
$var wire 64 H data_write_val [63:0] $end
$var wire 12 I csr_addr [11:0] $end
$var wire 64 J branch_offset [63:0] $end
$var wire 1 K alu_zero $end
$var wire 64 L alu_result [63:0] $end
$var wire 64 M alu_in_b [63:0] $end
$var wire 1 N VectorRegWrite $end
$var wire 1 O VectorOp $end
$var wire 1 P VectorMemWrite $end
$var wire 1 Q VectorMemRead $end
$var wire 3 R VALU_Op [2:0] $end
$var wire 1 S RegWrite $end
$var wire 2 T MemtoReg [1:0] $end
$var wire 1 U MemWrite $end
$var wire 1 V MemRead $end
$var wire 1 W Jump $end
$var wire 1 X CSR_Write $end
$var wire 1 Y CSR_Read $end
$var wire 1 Z Branch $end
$var wire 3 [ ALU_Op [2:0] $end
$var wire 1 \ ALUSrc_B $end
$var reg 64 ] csr_epc [63:0] $end
$var reg 64 ^ csr_trap_cause [63:0] $end
$var reg 64 _ csr_trap_handler [63:0] $end
$var reg 64 ` pc [63:0] $end
$var reg 64 a reg_write_data [63:0] $end
$var reg 64 b test_status [63:0] $end
$scope module u_alu $end
$var wire 64 c B [63:0] $end
$var wire 1 K Zero $end
$var wire 3 d ALU_Op [2:0] $end
$var wire 64 e A [63:0] $end
$var parameter 3 f ALU_ADD $end
$var parameter 3 g ALU_AND $end
$var parameter 3 h ALU_OR $end
$var parameter 3 i ALU_SHL $end
$var parameter 3 j ALU_SHR $end
$var parameter 3 k ALU_SUB $end
$var parameter 3 l ALU_XOR $end
$var reg 64 m Result [63:0] $end
$upscope $end
$scope module u_decoder $end
$var wire 32 n inst [31:0] $end
$var wire 5 o rs2 [4:0] $end
$var wire 5 p rs1 [4:0] $end
$var wire 5 q rd [4:0] $end
$var wire 8 r opcode [7:0] $end
$var wire 64 s imm19_sext [63:0] $end
$var wire 19 t imm19 [18:0] $end
$var wire 64 u imm14_sext [63:0] $end
$var wire 14 v imm14 [13:0] $end
$var wire 9 w funct9 [8:0] $end
$var wire 12 x csr_addr [11:0] $end
$var reg 1 \ ALUSrc_B $end
$var reg 3 y ALU_Op [2:0] $end
$var reg 1 Z Branch $end
$var reg 1 Y CSR_Read $end
$var reg 1 X CSR_Write $end
$var reg 1 W Jump $end
$var reg 1 V MemRead $end
$var reg 1 U MemWrite $end
$var reg 2 z MemtoReg [1:0] $end
$var reg 1 S RegWrite $end
$var reg 3 { VALU_Op [2:0] $end
$var reg 1 Q VectorMemRead $end
$var reg 1 P VectorMemWrite $end
$var reg 1 O VectorOp $end
$var reg 1 N VectorRegWrite $end
$upscope $end
$scope module u_regfile $end
$var wire 1 ( clk $end
$var wire 5 | rd [4:0] $end
$var wire 5 } rs1 [4:0] $end
$var wire 5 ~ rs2 [4:0] $end
$var wire 1 S we $end
$var wire 64 !" write_data [63:0] $end
$var wire 64 "" read_data2 [63:0] $end
$var wire 64 #" read_data1 [63:0] $end
$var integer 32 $" i [31:0] $end
$upscope $end
$scope module u_valu $end
$var wire 3 %" VALU_Op [2:0] $end
$var wire 2048 &" C [2047:0] $end
$var wire 2048 '" B [2047:0] $end
$var wire 2048 (" A [2047:0] $end
$var parameter 3 )" VALU_ADD $end
$var parameter 3 *" VALU_FMA $end
$var parameter 3 +" VALU_MUL $end
$var parameter 3 ," VALU_PERM $end
$var reg 2048 -" Result [2047:0] $end
$var reg 32 ." a_elem [31:0] $end
$var reg 32 /" b_elem [31:0] $end
$var reg 32 0" c_elem [31:0] $end
$var reg 32 1" res_elem [31:0] $end
$var integer 32 2" i [31:0] $end
$upscope $end
$scope module u_vrf $end
$var wire 1 ( clk $end
$var wire 5 3" rd [4:0] $end
$var wire 2048 4" read_data1 [2047:0] $end
$var wire 2048 5" read_data2 [2047:0] $end
$var wire 2048 6" read_data_vd [2047:0] $end
$var wire 5 7" rs1 [4:0] $end
$var wire 5 8" rs2 [4:0] $end
$var wire 1 N we $end
$var wire 2048 9" write_data [2047:0] $end
$var integer 32 :" i [31:0] $end
$upscope $end
$upscope $end
$scope begin $ivl_for_loop0 $end
$var integer 32 ;" i [31:0] $end
$upscope $end
$upscope $end
$enddefinitions $end
$comment Show the parameter values. $end
$dumpall
b11 ,"
b1 +"
b10 *"
b0 )"
b100 l
b1 k
b110 j
b101 i
b11 h
b10 g
b0 f
$end
#0
$dumpvars
b10000000000 ;"
b100000 :"
b0 9"
b0 8"
b0 7"
b0 6"
b0 5"
b0 4"
b10101 3"
b1000000 2"
b0 1"
b0 0"
b0 /"
b0 ."
b0 -"
b0 ("
b0 '"
b0 &"
b0 %"
b100000 $"
b0 #"
b0 ""
b1010 !"
b0 ~
b0 }
b10101 |
b0 {
b0 z
b0 y
b0 x
b1010 w
b1010 v
b1010 u
b1010 t
b1010 s
b1001 r
b10101 q
b0 p
b0 o
b1001101010000000000000001010 n
b1010 m
b0 e
b0 d
b1010 c
b0 b
b1010 a
b0 `
b0 _
b0 ^
b0 ]
1\
b0 [
0Z
0Y
0X
0W
0V
0U
b0 T
1S
b0 R
0Q
0P
0O
0N
b1010 M
b1010 L
0K
b101000 J
b0 I
b0 H
b1010 G
b1010 F
b1010 E
b1010 D
b1010 C
0B
b101000 A
b100 @
b1001 ?
b101000 >
b101000 =
b100 <
b10101 ;
b0 :
b0 9
b0 8
b0 7
b0 6
b0 5
b0 4
b0 3
b0 2
01
b1001101010000000000000001010 0
0/
b0 .
0-
b1010 ,
0+
0*
b0 )
0(
b1010 '
0&
0%
b0 $
b0 #
b0 "
b1001101010000000000000001010 !
$end
#5000
1(
#10000
0(
#15000
1(
#20000
0(
1*
#25000
b1010 a
b1010 !"
b1000 @
b1010 :
b1010 e
b1010 #"
0K
b1010 '
b1010 ,
b1010 L
b1010 m
b10101 8
b10101 p
b10101 }
b10101 7"
b0 M
b0 c
1\
1S
b1 ;
b1 q
b1 |
b1 3"
b0 E
b0 u
b0 J
b0 F
b0 v
b1111111111111111111111111111111111111111111111010100000000000000 C
b1111111111111111111111111111111111111111111111010100000000000000 s
b1111111111111111111111111111111111111111111101010000000000000000 A
b1010100000000000000 D
b1010100000000000000 t
b101010000000 I
b101010000000 x
b0 G
b0 w
b1001000011010100000000000000 !
b1001000011010100000000000000 0
b1001000011010100000000000000 n
b1000 <
b100 >
b1111111111111111111111111111111111111111111101010000000000000100 =
b100 #
b100 `
1(
#30000
0(
#35000
b0 a
b0 !"
1K
b0 '
b0 ,
b0 L
b0 m
b1100 @
b0 :
b0 e
b0 #"
b0 8
b0 p
b0 }
b0 7"
b10101 ;
b10101 q
b10101 |
b10101 3"
b0 C
b0 s
b0 A
b0 D
b0 t
b0 I
b0 x
b1001101010000000000000000000 !
b1001101010000000000000000000 0
b1001101010000000000000000000 n
b1100 <
b1000 >
b1000 =
b1000 #
b1000 `
1(
#40000
0(
#45000
b10000 @
b10101 8
b10101 p
b10101 }
b10101 7"
b10 ;
b10 q
b10 |
b10 3"
b1111111111111111111111111111111111111111111111010100000000000000 C
b1111111111111111111111111111111111111111111111010100000000000000 s
b1111111111111111111111111111111111111111111101010000000000000000 A
b1010100000000000000 D
b1010100000000000000 t
b101010000000 I
b101010000000 x
b1001000101010100000000000000 !
b1001000101010100000000000000 0
b1001000101010100000000000000 n
b10000 <
b1100 >
b1111111111111111111111111111111111111111111101010000000000001100 =
b1100 #
b1100 `
1(
#50000
0(
#55000
b1 a
b1 !"
b10100 @
0K
b1 '
b1 ,
b1 L
b1 m
b0 8
b0 p
b0 }
b0 7"
b1 M
b1 c
1\
1S
b10101 ;
b10101 q
b10101 |
b10101 3"
b1 E
b1 u
b100 J
b1 F
b1 v
b1 C
b1 s
b100 A
b1 D
b1 t
b0 I
b0 x
b1 G
b1 w
b1001101010000000000000000001 !
b1001101010000000000000000001 0
b1001101010000000000000000001 n
b10100 <
b10100 >
b10100 =
b10000 #
b10000 `
1(
#60000
0(
#65000
b1 a
b1 !"
b11000 @
b1 :
b1 e
b1 #"
0K
b1 '
b1 ,
b1 L
b1 m
b10101 8
b10101 p
b10101 }
b10101 7"
b0 M
b0 c
1\
1S
b11 ;
b11 q
b11 |
b11 3"
b0 E
b0 u
b0 J
b0 F
b0 v
b1111111111111111111111111111111111111111111111010100000000000000 C
b1111111111111111111111111111111111111111111111010100000000000000 s
b1111111111111111111111111111111111111111111101010000000000000000 A
b1010100000000000000 D
b1010100000000000000 t
b101010000000 I
b101010000000 x
b0 G
b0 w
b1001000111010100000000000000 !
b1001000111010100000000000000 0
b1001000111010100000000000000 n
b11000 <
b10100 >
b1111111111111111111111111111111111111111111101010000000000010100 =
b10100 #
b10100 `
1(
#70000
0(
#75000
b0 a
b0 !"
1K
b0 '
b0 ,
b0 L
b0 m
b11100 @
b0 :
b0 e
b0 #"
b0 8
b0 p
b0 }
b0 7"
b10101 ;
b10101 q
b10101 |
b10101 3"
b0 C
b0 s
b0 A
b0 D
b0 t
b0 I
b0 x
b1001101010000000000000000000 !
b1001101010000000000000000000 0
b1001101010000000000000000000 n
b11100 <
b11000 >
b11000 =
b11000 #
b11000 `
1(
#80000
0(
#85000
b100000 @
b10101 8
b10101 p
b10101 }
b10101 7"
b100 ;
b100 q
b100 |
b100 3"
b1111111111111111111111111111111111111111111111010100000000000000 C
b1111111111111111111111111111111111111111111111010100000000000000 s
b1111111111111111111111111111111111111111111101010000000000000000 A
b1010100000000000000 D
b1010100000000000000 t
b101010000000 I
b101010000000 x
b1001001001010100000000000000 !
b1001001001010100000000000000 0
b1001001001010100000000000000 n
b100000 <
b11100 >
b1111111111111111111111111111111111111111111101010000000000011100 =
b11100 #
b11100 `
1(
#90000
0(
#95000
b1 a
b1 !"
b100100 @
0K
b1 '
b1 ,
b1 L
b1 m
b0 8
b0 p
b0 }
b0 7"
b1 M
b1 c
1\
1S
b10101 ;
b10101 q
b10101 |
b10101 3"
b1 E
b1 u
b100 J
b1 F
b1 v
b1 C
b1 s
b100 A
b1 D
b1 t
b0 I
b0 x
b1 G
b1 w
b1001101010000000000000000001 !
b1001101010000000000000000001 0
b1001101010000000000000000001 n
b100100 <
b100100 >
b100100 =
b100000 #
b100000 `
1(
#100000
0(
#105000
b1 a
b1 !"
b101000 @
b1 :
b1 e
b1 #"
0K
b1 '
b1 ,
b1 L
b1 m
b10101 8
b10101 p
b10101 }
b10101 7"
b0 M
b0 c
1\
1S
b101 ;
b101 q
b101 |
b101 3"
b0 E
b0 u
b0 J
b0 F
b0 v
b1111111111111111111111111111111111111111111111010100000000000000 C
b1111111111111111111111111111111111111111111111010100000000000000 s
b1111111111111111111111111111111111111111111101010000000000000000 A
b1010100000000000000 D
b1010100000000000000 t
b101010000000 I
b101010000000 x
b0 G
b0 w
b1001001011010100000000000000 !
b1001001011010100000000000000 0
b1001001011010100000000000000 n
b101000 <
b100100 >
b1111111111111111111111111111111111111111111101010000000000100100 =
b100100 #
b100100 `
1(
#110000
0(
#115000
b101100 @
b101 8
b101 p
b101 }
b101 7"
b10110 ;
b10110 q
b10110 |
b10110 3"
b10100000000000000 C
b10100000000000000 s
b1010000000000000000 A
b10100000000000000 D
b10100000000000000 t
b1010000000 I
b1010000000 x
b1001101100010100000000000000 !
b1001101100010100000000000000 0
b1001101100010100000000000000 n
b101100 <
b101000 >
b1010000000000101000 =
b101000 #
b101000 `
1(
#120000
0(
#125000
b1 a
b1 !"
b110000 @
b0 :
b0 e
b0 #"
b1 '
b1 ,
b1 L
b1 m
b0 8
b0 p
b0 }
b0 7"
b1 M
b1 c
1\
1S
b10101 ;
b10101 q
b10101 |
b10101 3"
b1 E
b1 u
b100 J
b1 F
b1 v
b1 C
b1 s
b100 A
b1 D
b1 t
b0 I
b0 x
b1 G
b1 w
b1001101010000000000000000001 !
b1001101010000000000000000001 0
b1001101010000000000000000001 n
b110000 <
b110000 >
b110000 =
b101100 #
b101100 `
1(
#130000
0(
